task2dot/__init__.py
task2dot/task2dot.py
task2dot-0.0.15.dist-info/LICENSE
task2dot-0.0.15.dist-info/METADATA
task2dot-0.0.15.dist-info/WHEEL
task2dot-0.0.15.dist-info/entry_points.txt
task2dot-0.0.15.dist-info/top_level.txt
task2dot-0.0.15.dist-info/RECORD
