Metadata-Version: 2.1
Name: task2dot
Version: 0.0.15
Summary: Convert taskwarrior export to graphviz format and analyse projects
Home-page: https://github.com/garykl/task2dot
Author: Gary Klindt
Author-email: gary.klindt@gmail.com
License: UNKNOWN
Platform: UNKNOWN
Classifier: Programming Language :: Python :: 3
Classifier: License :: OSI Approved :: GNU General Public License v3 or later (GPLv3+)
Classifier: Operating System :: Unix
Requires-Python: >=3.6
